deeptile/__init__.py
deeptile/deeptile.py
deeptile/io.py
deeptile/core/__init__.py
deeptile/core/data.py
deeptile/core/iterators.py
deeptile/core/jobs.py
deeptile/core/lift.py
deeptile/core/process.py
deeptile/core/profiles.py
deeptile/core/trees.py
deeptile/core/utils.py
deeptile/extensions/__init__.py
deeptile/extensions/segmentation.py
deeptile/extensions/stitch.py
deeptile/sources/__init__.py
deeptile/sources/array.py
deeptile/sources/function.py
deeptile/sources/large_image.py
deeptile/sources/nd2.py
deeptile/sources/tiff.py
deeptile-2.0.10.dist-info/licenses/LICENSE
deeptile-2.0.10.dist-info/METADATA
deeptile-2.0.10.dist-info/WHEEL
deeptile-2.0.10.dist-info/top_level.txt
deeptile-2.0.10.dist-info/RECORD
