Metadata-Version: 2.4
Name: DeepTile
Version: 2.0.10
Summary: Large image tiling and stitching library for scaling Python functions to arbitrary input image sizes.
Author: William Niu
Author-email: wniu721@gmail.com
Keywords: machine learning,deep learning,image tiling,image stitching
Classifier: Development Status :: 5 - Production/Stable
Classifier: Programming Language :: Python
Requires-Python: >=3.8
License-File: LICENSE
Requires-Dist: dask
Requires-Dist: nd2
Requires-Dist: numpy
Requires-Dist: tifffile
Dynamic: license-file
